{
  "usuarios": [
    {
      "nome": "ddsad",
      "user": "12345",
      "senha": "123456",
      "id": 1
    }
  ],
  "recursos": [
    {
      "pc": 7800,
      "id": 1
    }
  ],
  "itens":[
    {
    "id":1,
    "nome": "Troféu 1",
    "img":"imagens/TROPHY1.png",
    "valor": "10000",
    "rank":"1"
    },
    {
    "id":2,
    "nome": "Troféu 2",
    "img":"",
    "valor": "50000",
    "rank":"5"
    },
    {
    "id":3,
    "nome": "Troféu 3",
    "img":"",
    "valor": "100000",
    "rank":"10"
    }

],
  "tarefa": [
    {
      "nome": "cfssdf",
      "inicio": "10:00",
      "fim": "11:00",
      "necessario": false,
      "obs": "",
      "dia": "dom",
      "id": 1
    },
    {
      "nome": "jfdsjksdfjklsdfljk",
      "inicio": "01:00",
      "fim": "20:20",
      "necessario": false,
      "obs": "",
      "dia": "seg",
      "id": 2
    }
  ]
}